{
  "type": "minecraft:chest",
  "pools": [
    {
      "rolls": 1,
      "entries": [
        {
          "type": "minecraft:alternatives",
          "children": [
            {
              "type": "minecraft:loot_table",
              "name": "nincodedo:uniqueitems/mastersword",
              "conditions": [
                {
                  "condition": "minecraft:value_check",
                  "value": {
                    "type": "minecraft:score",
                    "target": {
                      "type": "minecraft:fixed",
                      "name": "mastersword"
                    },
                    "score": "rhcdata"
                  },
                  "range": 0
                }
              ]
            },
            {
              "type": "minecraft:loot_table",
              "name": "nincodedo:uniqueitems/nightvision",
              "conditions": [
                {
                  "condition": "minecraft:value_check",
                  "value": {
                    "type": "minecraft:score",
                    "target": {
                      "type": "minecraft:fixed",
                      "name": "global"
                    },
                    "score": "goggles"
                  },
                  "range": 0
                }
              ]
            },
            {
              "type": "minecraft:loot_table",
              "name": "nincodedo:uniqueitems/sheephorn",
              "conditions": [
                {
                  "condition": "minecraft:value_check",
                  "value": {
                    "type": "minecraft:score",
                    "target": {
                      "type": "minecraft:fixed",
                      "name": "global"
                    },
                    "score": "sheephorn"
                  },
                  "range": 0
                }
              ]
            },
            {
              "type": "minecraft:loot_table",
              "name": "nincodedo:uniqueitems/iridiumrod",
              "conditions": [
                {
                  "condition": "minecraft:value_check",
                  "value": {
                    "type": "minecraft:score",
                    "target": {
                      "type": "minecraft:fixed",
                      "name": "iridiumrod"
                    },
                    "score": "rhcdata"
                  },
                  "range": 0
                }
              ]
            },
            {
              "type": "minecraft:loot_table",
              "name": "nincodedo:uniqueitems/torchbow",
              "conditions": [
                {
                  "condition": "minecraft:value_check",
                  "value": {
                    "type": "minecraft:score",
                    "target": {
                      "type": "minecraft:fixed",
                      "name": "torchbow"
                    },
                    "score": "rhcdata"
                  },
                  "range": 0
                }
              ]
            },
            {
              "type": "minecraft:loot_table",
              "name": "nincodedo:uniqueitems/potionhorn",
              "conditions": [
                {
                  "condition": "minecraft:value_check",
                  "value": {
                    "type": "minecraft:score",
                    "target": {
                      "type": "minecraft:fixed",
                      "name": "potionhorn"
                    },
                    "score": "rhcdata"
                  },
                  "range": 0
                }
              ]
            },
            {
              "type": "minecraft:loot_table",
              "name": "nincodedo:uniqueitems/potionbundle",
              "conditions": [
                {
                  "condition": "minecraft:value_check",
                  "value": {
                    "type": "minecraft:score",
                    "target": {
                      "type": "minecraft:fixed",
                      "name": "potionhorn"
                    },
                    "score": "rhcdata"
                  },
                  "range": 1
                }
              ]
            },
            {
              "type": "minecraft:loot_table",
              "name": "nincodedo:uniqueitems/ascend",
              "conditions": [
                {
                  "condition": "minecraft:value_check",
                  "value": {
                    "type": "minecraft:score",
                    "target": {
                      "type": "minecraft:fixed",
                      "name": "mastersword"
                    },
                    "score": "rhcdata"
                  },
                  "range": 1
                }
              ]
            }
          ]
        }
      ]
    }
  ]
}
